README.md
license.txt
setup.cfg
setup.py
aueno_distributions.egg-info/PKG-INFO
aueno_distributions.egg-info/SOURCES.txt
aueno_distributions.egg-info/dependency_links.txt
aueno_distributions.egg-info/not-zip-safe
aueno_distributions.egg-info/top_level.txt
distributions/Binomialdistribution.py
distributions/Gaussiandistribution.py
distributions/Generaldistribution.py
distributions/__init__.py