Metadata-Version: 2.1
Name: aueno-distributions
Version: 0.0.2
Summary: Gaussian and Binomial distributions
Home-page: https://www.example.com/aueno-distributions/
Author: Akito Ueno
Author-email: satsudai200411078@yahoo.co.jp
License: MIT # License Name
Platform: UNKNOWN
